{
  "GAME": "Chain Reaction",
  "DEVELOPER": "Ankush Patil",
  "GRID_SIZE": "8",
  "PLAYER_COUNT": "2",
  "PLAYER_ONE": "red",
  "PLAYER_TWO": "blue",
  "PLAYER_THREE": "green",
  "PLAYER_FOUR": "yellow",
  "PLAYER_FIVE": "orange",
  "PLAYER_SIX": "maroon",
  "PLAYER_SEVEN": "cadetblue",
  "PLAYER_EIGHT": "aqua",
  "NO_PLAYER": "white",
  "red": "PLAYER ONE",
  "blue": "PLAYER TWO",
  "green": "PLAYER THREE",
  "yellow": "PLAYER FOUR",
  "orange": "PLAYER FIVE",
  "maroon": "PLAYER SIX",
  "cadetblue": "PLAYER SEVEN",
  "aqua": "PLAYER EIGHT",
  "PLAYER_COLOR_MAP": {
    "2": ["red", "blue"],
    "3": ["red", "blue", "green"],
    "4": ["red", "blue", "green", "yellow"],
    "5": ["red", "blue", "green", "yellow", "orange"],
    "6": ["red", "blue", "green", "yellow", "orange", "maroon"],
    "7": ["red", "blue", "green", "yellow", "orange", "maroon", "cadetblue"],
    "8": [
      "red",
      "blue",
      "green",
      "yellow",
      "orange",
      "maroon",
      "cadetblue",
      "aqua"
    ]
  }
}
